commitlm/__init__.py
commitlm/cli/__init__.py
commitlm/cli/commands.py
commitlm/cli/init_command.py
commitlm/config/__init__.py
commitlm/config/prompts.py
commitlm/config/settings.py
commitlm/core/__init__.py
commitlm/core/llm_client.py
commitlm/integrations/__init__.py
commitlm/integrations/git_client.py
commitlm/utils/__init__.py
commitlm/utils/helpers.py
commitlm-1.0.9.dist-info/licenses/LICENSE
commitlm-1.0.9.dist-info/licenses/NOTICE
commitlm-1.0.9.dist-info/METADATA
commitlm-1.0.9.dist-info/WHEEL
commitlm-1.0.9.dist-info/entry_points.txt
commitlm-1.0.9.dist-info/top_level.txt
commitlm-1.0.9.dist-info/RECORD
