Metadata-Version: 2.4
Name: commitlm
Version: 1.0.9
Summary: AI-powered Git Documentation & Commit Messages
Author-email: Sin Liang Lee <sinlianglee110@gmail.com>
License-Expression: Apache-2.0
Project-URL: Homepage, https://github.com/LeeSinLiang/commitLM
Project-URL: Repository, https://github.com/LeeSinLiang/commitLM
Project-URL: Issues, https://github.com/LeeSinLiang/commitLM/issues
Project-URL: Changelog, https://github.com/LeeSinLiang/commitLM/releases
Keywords: git,commit,documentation,ai,llm,automation,developer-tools
Classifier: Development Status :: 4 - Beta
Classifier: Intended Audience :: Developers
Classifier: Programming Language :: Python :: 3
Classifier: Programming Language :: Python :: 3.9
Classifier: Programming Language :: Python :: 3.10
Classifier: Programming Language :: Python :: 3.11
Classifier: Programming Language :: Python :: 3.12
Classifier: Operating System :: OS Independent
Classifier: Topic :: Software Development :: Version Control :: Git
Classifier: Topic :: Software Development :: Documentation
Classifier: Topic :: Text Processing :: Linguistic
Requires-Python: >=3.9
License-File: LICENSE
License-File: NOTICE
Requires-Dist: gitpython
Requires-Dist: transformers>=4.35.0
Requires-Dist: torch>=2.0.0
Requires-Dist: accelerate
Requires-Dist: optimum[cpu]
Requires-Dist: click>=8.0
Requires-Dist: pydantic>=2.0
Requires-Dist: jinja2
Requires-Dist: rich
Requires-Dist: python-dotenv
Requires-Dist: watchdog
Requires-Dist: google-genai
Requires-Dist: google-api-core
Requires-Dist: anthropic
Requires-Dist: openai
Requires-Dist: InquirerPy
Provides-Extra: dev
Requires-Dist: pytest>=7.0; extra == "dev"
Requires-Dist: pytest-cov; extra == "dev"
Requires-Dist: black; extra == "dev"
Requires-Dist: ruff; extra == "dev"
Requires-Dist: mypy; extra == "dev"
Requires-Dist: build; extra == "dev"
Requires-Dist: twine; extra == "dev"
Dynamic: license-file
